cemm_gen/__init__.py
cemm_gen/convert.py
cemm_gen/make_param.py
cemm_gen/model.py
cemm_gen/protein.py
cemm_gen/utils.py
cemm_gen/share/FF_PARAM/FF_AMO/AMO.frcmod
cemm_gen/share/FF_PARAM/FF_AMO/AMO.lib
cemm_gen/share/FF_PARAM/FF_AMO/AMO.mol2
cemm_gen/share/FF_PARAM/FF_AMO/AMO.pdb
cemm_gen/share/FF_PARAM/FF_AMO/AMO_orig.mol2
cemm_gen/share/FF_PARAM/FF_AMO/AMO_orig_round.mol2
cemm_gen/share/FF_PARAM/FF_AMO/AMO_partialChgs.mol2
cemm_gen/share/FF_PARAM/FF_AMO/AMO_psi4.mol2
cemm_gen/share/FF_PARAM/FF_AMO/description.txt
cemm_gen/share/FF_PARAM/FF_AMO/leap.in
cemm_gen/share/FF_PARAM/FF_AMO/smiles.png
cemm_gen/share/FF_PARAM/FF_AMO/smiles.txt
cemm_gen/share/FF_PARAM/FF_AMO/smiles_ETKDGv3.png
cemm_gen/share/FF_PARAM/FF_AMO/smiles_charges.png
cemm_gen/share/FF_PARAM/FF_ARM/ARM.frcmod
cemm_gen/share/FF_PARAM/FF_ARM/ARM.lib
cemm_gen/share/FF_PARAM/FF_ARM/ARM.mol2
cemm_gen/share/FF_PARAM/FF_ARM/ARM.pdb
cemm_gen/share/FF_PARAM/FF_ARM/ARM_orig.mol2
cemm_gen/share/FF_PARAM/FF_ARM/ARM_orig_round.mol2
cemm_gen/share/FF_PARAM/FF_ARM/ARM_partialChgs.mol2
cemm_gen/share/FF_PARAM/FF_ARM/ARM_psi4.mol2
cemm_gen/share/FF_PARAM/FF_ARM/description.txt
cemm_gen/share/FF_PARAM/FF_ARM/leap.in
cemm_gen/share/FF_PARAM/FF_ARM/smiles.png
cemm_gen/share/FF_PARAM/FF_ARM/smiles.txt
cemm_gen/share/FF_PARAM/FF_ARM/smiles_ETKDGv3.png
cemm_gen/share/FF_PARAM/FF_ARM/smiles_charges.png
cemm_gen/share/FF_PARAM/FF_ARO/ARO.frcmod
cemm_gen/share/FF_PARAM/FF_ARO/ARO.lib
cemm_gen/share/FF_PARAM/FF_ARO/ARO.mol2
cemm_gen/share/FF_PARAM/FF_ARO/ARO.pdb
cemm_gen/share/FF_PARAM/FF_ARO/ARO_orig.mol2
cemm_gen/share/FF_PARAM/FF_ARO/ARO_orig_round.mol2
cemm_gen/share/FF_PARAM/FF_ARO/ARO_partialChgs.mol2
cemm_gen/share/FF_PARAM/FF_ARO/ARO_psi4.mol2
cemm_gen/share/FF_PARAM/FF_ARO/description.txt
cemm_gen/share/FF_PARAM/FF_ARO/leap.in
cemm_gen/share/FF_PARAM/FF_ARO/smiles.png
cemm_gen/share/FF_PARAM/FF_ARO/smiles.txt
cemm_gen/share/FF_PARAM/FF_ARO/smiles_ETKDGv3.png
cemm_gen/share/FF_PARAM/FF_ARO/smiles_charges.png
cemm_gen-2024.7.23.dist-info/LICENSE
cemm_gen-2024.7.23.dist-info/METADATA
cemm_gen-2024.7.23.dist-info/WHEEL
cemm_gen-2024.7.23.dist-info/entry_points.txt
cemm_gen-2024.7.23.dist-info/top_level.txt
cemm_gen-2024.7.23.dist-info/RECORD
